LICENSE
MANIFEST.in
README.md
setup.cfg
setup.py
dagster_airbyte/__init__.py
dagster_airbyte/asset_defs.py
dagster_airbyte/cli.py
dagster_airbyte/ops.py
dagster_airbyte/py.typed
dagster_airbyte/resources.py
dagster_airbyte/types.py
dagster_airbyte/utils.py
dagster_airbyte/version.py
dagster_airbyte/managed/__init__.py
dagster_airbyte/managed/reconciliation.py
dagster_airbyte/managed/types.py
dagster_airbyte/managed/generated/__init__.py
dagster_airbyte/managed/generated/destinations.py
dagster_airbyte/managed/generated/sources.py
prime_dagster_airbyte.egg-info/PKG-INFO
prime_dagster_airbyte.egg-info/SOURCES.txt
prime_dagster_airbyte.egg-info/dependency_links.txt
prime_dagster_airbyte.egg-info/entry_points.txt
prime_dagster_airbyte.egg-info/not-zip-safe
prime_dagster_airbyte.egg-info/requires.txt
prime_dagster_airbyte.egg-info/top_level.txt