Metadata-Version: 2.1
Name: prime-dagster-airbyte
Version: 0.19.13.dev1
Summary: Package for integrating Airbyte with Dagster.
Home-page: https://github.com/huylenq/dagster/tree/master/python_modules/libraries/dagster-airbyte
Author: Elementl, Huy
Author-email: huy.lenq@gmail.com
License: Apache-2.0
Classifier: Programming Language :: Python :: 3.7
Classifier: Programming Language :: Python :: 3.8
Classifier: Programming Language :: Python :: 3.9
Classifier: Programming Language :: Python :: 3.10
Classifier: Programming Language :: Python :: 3.11
Classifier: License :: OSI Approved :: Apache Software License
Classifier: Operating System :: OS Independent
Provides-Extra: test
Provides-Extra: managed
License-File: LICENSE
